{
    "110": {
        "number": 110,
        "bab": 3,
        "title": "زیارت وداع امام هشتم، حضرت امام رضا(ع)",
        "arabic": {
            "1": "\r\nالسَّلامُ عَلَيْكَ يَا وَلِيَّ اللَّهِ وَ رَحْمَةُ اللَّهِ وَ بَرَكَاتُهُ اللَّهُمَّ لا تَجْعَلْهُ آخِرَ الْعَهْدِ مِنْ زِيَارَتِي ابْنَ نَبِيِّكَ وَ حُجَّتَكَ عَلَى خَلْقِكَ وَ اجْمَعْنِي وَ إِيَّاهُ فِي جَنَّتِكَ وَ احْشُرْنِي مَعَهُ وَ فِي حِزْبِهِ مَعَ الشُّهَدَاءِ وَ الصَّالِحِينَ وَ حَسُنَ أُولَئِكَ رَفِيقاً وَ أَسْتَوْدِعُكَ اللَّهَ وَ أَسْتَرْعِيكَ وَ أَقْرَأُ عَلَيْكَ السَّلامَ آمَنَّا بِاللَّهِ وَ بِالرَّسُولِ وَ بِمَا جِئْتَ بِهِ وَ دَلَلْتَ عَلَيْهِ فَاكْتُبْنَا مَعَ الشَّاهِدِينَ\r\n",
            "2": "\r\n"
        },
        "farsi": {
            "1": " سلام و رحمت و بركات خدا بر تو باد اى ولىّ خدا.خدايا اين زيارت را آخرين بار از زيارت من‏\r\nفرزند پيامبرت،و حجّت بر بندگانت قرا رمده،و من و او را در بهشت گردآور،و با او در حزبش محشور كن‏\r\nهمراه با شهدا و شايستگان،و آنان از جهت رفيق بودن خوبند،و به خدا می سپارمت،و خواستار رعايت توام،و\r\nبر تو سلام مى ‏خوانم،به خدا و به پيامبر و به آنچه تو آوردى و بر آن دلالت نمودى ايمان آورديم،پس ما را\r\nبا گواهان بنويس."
        },
        "tozih": {
            "1": " مؤلّف گويد:زيارت آن حضرت در ايّام و اوقات شريفه خاصه به آن‏\r\nجناب فضيلت بسيار دارد،به ويژه در ماه رجب و بيست‏ و سوم و بيست‏ و پنجم ذو القعده،و ششم ماه رمضان،\r\nچنان‏كه در محل خود در اعمال ماهها ذكر شد،و غير اين روزها از ايام ديگر،كه به آن حضرت اختصاصى دارد.چون‏\r\nخواستى آن حضرت را وداع كنى،آنچه را در وداع حضرت رسول صلى اللّه عليه و آله میگفتى بگو:«لا جلعه اللّه آخر\r\nتسليمى عليك...»و اگر خواستى بگو:"
        }
    }
}