{
    "290": {
        "number":290 ,
        "bab": 76,
        "title": "خواص سوره ملک",
        "arabic": {
            "1": " ",
            "2": "",
            "3": "",
            "4": "",
            "5": "",
            "6": "",
            "7": ""

        },
        "farsi": {
            "1": "",
            "2": "",
            "3": "",
            "4": "",
            "5": "",
            "6": "",
            "7": ""

        },
        "tozih": {
            "1": "کلینی از حضرت باقر(علیه\u200Cالسلام) روایت کرده: سوره «ملک» بازدارنده است، از عذاب قبر بازدارد... تا پایان روایت.",
            "2": "",
            "3": "",
            "4": "",
            "5": "",
            "6": "",
            "7": ""

        }
    }
}