{
    "246": {
        "number": 246,
        "bab": 3,
        "title": "فضیلت زیارت امام حسین(ع)   ",
        "arabic": {
            "1": "\r\n",
            "2": "\r\n"
        },
        "farsi": {
            "1": " پس رحم كن آن صورت ها را كه آفتاب تغيير داده و رحم كن گونه هاى آنان را كه بر\r\nقبر امام حسين عليه السلام می گردانند."
        },
        "tozih": {
            "1": "فصل هفتم",
            "2": " و رحم كن آن ديده ها را كه براى دلسوزى بر ما اشكشان جارى شد و رحم كن آن دل ها را كه زارى كردند،و سوختند براى مصيبت ما،\r\nو رحم كن آن صداها را كه در مصيبت ما بلند كرده اند.خدايا آن جان ها و بدن ها را به تو میسپارم،تا آنها را از حوض كوثر در\r\nروز تشنگى سيراب كنى و پيوسته آن حضرت به اين صورت در سجده دعا میكرد،چون فارغ شدى،عرضه داشتم،اين دعايی\r\nكه من از شما شنيدم،اگر در حق كسى میكرديد كه خدا را نمیشناخت،گمان داشتم هرگز آتش دوزخ به او نرسد،و اللّه \r\nآرزو كردم كه آن حضرت را زيارت كرده بودم و حجّ انجام نداده بودم!!امام فرمود:تو چه بسيار نزديكى به آن حضرت \r\nتو را از زيارت چه چيز مانع است؟معاويه ترك زيارت مكن،گفتم:فدايت شوم،نمیدانستم اين اندازه فضيلت \r\nدارد،فرمود:اى معاويه،آنها كه در آسمان براى زيارت كنندگان آن حضرت دعا می كنند،زياده از آنهايند كه در\r\nزمين دعا میكنند،زيارت آن حضرت را براى ترس از احدى ترك مكن،كه هركس به خاطر ترس،ترك زيارت كند\r\nآن قدر حسرت ميبرد،كه آرزو میكند اى كاش به اندازه اى نزد قبر آن حضرت میماندم كه در آنجا دفن میشدم!آيا دوست \r\nندارى خدا تو را در ميان آنهايى كه رسول خدا و على و فاطمه و امامان معصوم عليهم السّلام بر آنها دعا میكنند؟ببيند آيا نمیخواهى از\r\nآنها باشى كه ملائكه در قيامت با آنان مصافحه می كنند؟آيا نمی خواهى از آنها باشى كه در قيامت وارد شوند و هيچ گناهى بر\r\nآنها نباشد؟آيا نمی خواهى از آنها باشى كه در قيامت رسول خدا صلّى اللّه عليه و آله و سلّم با آنان مصافحه می كند؟!"
        }
    }
}