{
    "416": {
        "number": 416,
        "bab": 6,
        "title": "نماز گرسنه",
        "arabic": {
            "1": "\r\nيا رَبِّ اِنّى جائِعٌ فَاَطْعِمْنى\r\n",
            "2": "\r\nرَبِّ اَطْعِمْنى فَاِنّى جائِعٌ\r\n",
            "3": "\r\n\r\n"
        },
        "farsi": {
            "1": " اى پروردگارم،من گرسنه هستم طعامم بده",
            "2": " پروردگارا خوراكم ده من گرسنه"
        },
        "tozih": {
            "1": " از حضرت صادق عليه السّلام روايت شده:هركه‏\r\nگرسنه باشد وضو بگيرد،و دو ركعت نماز گذارد،و بگويد:",
            "2": "و در روايت ديگری آمده است: ",
            "3": "به درستى كه خدا او را در آن ساعت طعام دهد."
        }
    }
}