{
    "242": {
        "number": 242,
        "bab": 2,
        "title": "اعمال روز بیست و پنجم ذی الحجه",
        "arabic": {
            "1": " style=\"font-weight:bold;color:#5E2901;font-size:100%;direction:rtl;display:inline\"«هَل اَتی»/",
            "2": " در حق اهل‌بیت نازل شد برای اینکه سه روز روزه گرفتند و افطاری خود را به مسکین و یتیم و اسیر دادند و خود با آب افطار نمودند!/",
            "3": "\n/p"
        },
        "farsi": {},
        "tozih": {
            "1": " روز بیست  و پنجم که روز بس شریفی است و روزی است که سوره «هَل اَتی» در حق اهل‌بیت نازل شد برای اینکه سه روز روزه گرفتند و افطاری خود را به مسکین و یتیم و اسیر دادند و خود با آب افطار نمودند!",
            "2": "و سزاوار است شیعیان اهل‌بیت در این ایام به ویژه در شب بیست‌وپنجم در دادن صدقه به مساکین و ایتام و سعی در اطعام ایشان و روزه داشتن این روز و پیروی از مولایان خود کنند.",
            "3": "از آنجا که بعضی از علما این روز را روز مباهله می‌دانند، مناسب است «زیارت جامعه» و  «دعای مباهله»  را نیز در این روز بخوانند. "
        }
    }
}