{
    "17": {
        "number": 17,
        "bab": 10,
        "title": "مذمت و نکوهش تراشیدن ریش",
        "arabic": {
            "1": "\r\n"
        },
        "farsi": {},
        "tozih": {
            "1": " لذا در بسيارى از روايات وارد شده:فلان عمل را بجا آوريد،و خود را به كفّار شبيه نسازيد،مانند روايتى كه از رسول‏\r\nخدا صلّى اللّه عليه و آله و سلّم نقل شده:شارب[موهاى پشت لب]را از ته بگيريد،و محاسن[موهاى صورت]را بلند بگذاريد،و خود را به يهوديان و گبران‏\r\nشبيه نكنيد،و نيز فرمود:گبران محاسن خود را تراشيدند،و شاربهاى خود را زياد كردند،و ما شارب خود را مى‏گيريم و محاسن مى‏گذاريم،\r\nو هنگامى‏كه نامه‏هاى دعوت آن جناب به پادشاهان رسيد،كسرى به باذان عامل يمن نوشت،آن حضرت را نزد او فرستد،و او كاتب خود\r\nبانويه،و مردى كه او را خرحسنك مى‏گفتند به مدينه فرستاد،و آن دو محاسن خود را تراشيده و شارب گذاشته بودند،آن جناب را خوش نيامد\r\nكه به ايشان نظر كند فرمود:واى بر شما چه كسى شما را به اين هيئت امر كرده؟گفتند:پروردگارمان يعنى كسرى،فرمود ولى پروردگار من مرا\r\nبه گذاشتن محاسن و چيدن شارب امر فرموده است."
        }
    }
}