{
    "4": {
        "number": 4,
        "bab": 1,
        "title": "دعای حضرت یوسف(ع) در زندان",
        "arabic": {
            "1": "  اللّٰهُمَّ صَلِّ عَلَىٰ مُحَمَّدٍ وَآلِ مُحَمَّدٍ ، وَاجْعَلْ لِى مِنْ أَمْرِىَ فَرَجاً وَمَخْرَجاً ، وَارْزُقْنِى مِنْ حَيْثُ أَحْتَسِبُ وَمِنْ حَيْثُ لَاأَحْتَسِبُ. \r\n",
            "2": "\n"
        },
        "farsi": {
            "1": "خدایا! درود فرست بر محمّد و خاندان محمّد و در کارم برای من گشایش و راه نجات قرار ده و مرا از جانبی که گمان می‌برم و از جانبی که گمان نمی‌برم، روزی عنایت کن. "
        },
        "tozih": {
            "1": "و این دعایی است که جبرئیل آن را به حضرت یوسف(علیه‌السلام) هنگامی‌که آن حضرت در زندان بود تعلیم داد."
        }
    }
}