{
    "64": {
        "number": 64,
        "bab": 2,
        "title": "دعای روز سی ام ماه رمضان",
        "arabic": {
            "1": "\r\nاللَّهُمَّ اشْرَحْ بِالْقُرْآنِ صَدْرِي وَ اسْتَعْمِلْ بِالْقُرْآنِ بَدَنِي وَ نَوِّرْ بِالْقُرْآنِ بَصَرِي وَ أَطْلِقْ بِالْقُرْآنِ لِسَانِي وَ أَعِنِّي عَلَيْهِ مَا أَبْقَيْتَنِي فَإِنَّهُ لا حَوْلَ وَ لا قُوَّةَ إِلا بِكَ.\r\n",
            "2": " \r\nاللَّهُمَّ إِنِّي أَسْأَلُكَ إِخْبَاتَ الْمُخْبِتِينَ وَ إِخْلاصَ الْمُوقِنِينَ وَ مُرَافَقَةَ الْأَبْرَارِ وَ اسْتِحْقَاقَ حَقَائِقِ الْإِيمَانِ وَ الْغَنِيمَةَ مِنْ كُلِّ بِرٍّ وَ السَّلامَةَ مِنْ كُلِّ إِثْمٍ وَ وُجُوبَ رَحْمَتِكَ وَ عَزَائِمَ مَغْفِرَتِكَ وَ الْفَوْزَ بِالْجَنَّةِ وَ النَّجَاةَ مِنَ النَّارِ\r\n",
            "3": "\r\n"
        },
        "farsi": {
            "1": " خدايا،به قرآن سينه‏ ام را بگشا،و به قرآن بدنم را بكار انداز،و به قرآن ديده‏ ام را روشن ساز،و به‏\r\nقرآن زبانم را بازگردان،و به عمل به آن تا زنده ‏ام می دارى يارى ‏ام ده،كه جنبش و نيرويى جز به خواست تو نيست.",
            "2": " خدايا از تو درخواست مى ‏كنم،خشوع خاشعان،و اخلاص اهل يقين،و مداراى نيكان،و شايستگی\r\nحقايق ايمان،و بهره ‏مندى از هر نيكى،و سلامت از هر گناه،و وجوب رحمتت،و اراده‏ های\r\nآمرزشت،و رسيدن به بهشت،و رهايى از آتش را."
        },
        "tozih": {
            "1": " روز سى ‏ام:سيّد در كتاب«اقبال»براى روز آخر دعايى نقل كرده است كه ابتدايش اين ات:الّلهم انّك ارحم‏\r\nالرّاحمين و چون در اين روز بيشتر مردم قرآن را ختم میكنند،شايسته است پس از ختم قرآن دعاى چهل‏ودوم صحيفه كامله سجاديه‏\r\nرا بخوانند و اگر بخواهند میتوانند اين دعاى مختصر را كه شيخ طوسى از امير المؤمنين عليه السّلام روايت كرده بخوانند:",
            "2": " و همچنين اين دعا را كه از حضرت امير المؤمنين عليه السّلام روايت شده است بخواند:"
        }
    }
}